metient/__init__.py
metient/example.py
metient/metient.py
metient/lib/__init__.py
metient/lib/metient.py
metient/lib/vertex_labeling.py
metient/util/__init__.py
metient/util/create_conf_intervals_from_reads.py
metient/util/data_extraction_util.py
metient/util/eval_util.py
metient/util/extra.py
metient/util/globals.py
metient/util/pairtree_data_extraction_util.py
metient/util/plotting_util.py
metient/util/vertex_labeling_util.py
src/__init__.py
src/example.py
src/lib/__init__.py
src/lib/metient.py
src/lib/vertex_labeling.py
src/util/__init__.py
src/util/create_conf_intervals_from_reads.py
src/util/data_extraction_util.py
src/util/eval_util.py
src/util/extra.py
src/util/globals.py
src/util/pairtree_data_extraction_util.py
src/util/plotting_util.py
src/util/vertex_labeling_util.py
metient-1.1.0.dist-info/METADATA
metient-1.1.0.dist-info/WHEEL
metient-1.1.0.dist-info/top_level.txt
metient-1.1.0.dist-info/RECORD
