Metadata-Version: 2.1
Name: metient
Version: 1.1.0
Home-page: https://github.com/divyakoyy/metient.git
Requires-Dist: alsa-lib ==1.2.3.2
Requires-Dist: anyio ==3.7.1
Requires-Dist: argon2-cffi ==21.3.0
Requires-Dist: argon2-cffi-bindings ==21.2.0
Requires-Dist: arrow ==1.2.3
Requires-Dist: asttokens ==2.2.1
Requires-Dist: async-lru ==2.0.4
Requires-Dist: atk ==2.36.0
Requires-Dist: atk-1.0 ==2.36.0
Requires-Dist: attrs ==23.1.0
Requires-Dist: babel ==2.12.1
Requires-Dist: backcall ==0.2.0
Requires-Dist: backports ==1.0
Requires-Dist: backports.functools-lru-cache ==1.6.5
Requires-Dist: beautifulsoup4 ==4.12.2
Requires-Dist: bleach ==6.0.0
Requires-Dist: brotli ==1.0.9
Requires-Dist: brotli-bin ==1.0.9
Requires-Dist: brotli-python ==1.0.9
Requires-Dist: bzip2 ==1.0.8
Requires-Dist: ca-certificates ==2023.7.22
Requires-Dist: cached-property ==1.5.2
Requires-Dist: cairo ==1.16.0
Requires-Dist: certifi ==2023.7.22
Requires-Dist: cffi ==1.14.4
Requires-Dist: charset-normalizer ==3.2.0
Requires-Dist: comm ==0.1.4
Requires-Dist: contourpy ==1.1.0
Requires-Dist: cycler ==0.11.0
Requires-Dist: dbus ==1.13.6
Requires-Dist: debugpy ==1.6.8
Requires-Dist: decorator ==5.1.1
Requires-Dist: defusedxml ==0.7.1
Requires-Dist: entrypoints ==0.4
Requires-Dist: exceptiongroup ==1.1.3
Requires-Dist: executing ==1.2.0
Requires-Dist: expat ==2.5.0
Requires-Dist: filelock ==3.12.2
Requires-Dist: flit-core ==3.9.0
Requires-Dist: font-ttf-dejavu-sans-mono ==2.37
Requires-Dist: font-ttf-inconsolata ==3.000
Requires-Dist: font-ttf-source-code-pro ==2.038
Requires-Dist: font-ttf-ubuntu ==0.83
Requires-Dist: fontconfig ==2.14.2
Requires-Dist: fonts-conda-ecosystem ==1
Requires-Dist: fonts-conda-forge ==1
Requires-Dist: fonttools ==4.42.1
Requires-Dist: fqdn ==1.5.1
Requires-Dist: freetype ==2.12.1
Requires-Dist: fribidi ==1.0.10
Requires-Dist: gdk-pixbuf ==2.42.2
Requires-Dist: gettext ==0.21.1
Requires-Dist: giflib ==5.2.1
Requires-Dist: glib ==2.66.3
Requires-Dist: gmp ==6.2.1
Requires-Dist: gobject-introspection ==1.66.1
Requires-Dist: graphite2 ==1.3.13
Requires-Dist: graphviz ==2.42.3
Requires-Dist: gst-plugins-base ==1.14.5
Requires-Dist: gstreamer ==1.14.5
Requires-Dist: gtk2 ==2.24.32
Requires-Dist: gts ==0.7.6
Requires-Dist: harfbuzz ==2.7.2
Requires-Dist: icu ==67.1
Requires-Dist: idna ==3.4
Requires-Dist: importlib-metadata ==6.8.0
Requires-Dist: importlib-resources ==6.0.1
Requires-Dist: ipykernel ==6.25.1
Requires-Dist: ipython ==8.12.2
Requires-Dist: ipython-genutils ==0.2.0
Requires-Dist: ipywidgets ==8.1.0
Requires-Dist: isoduration ==20.11.0
Requires-Dist: jedi ==0.19.0
Requires-Dist: jinja2 ==3.1.2
Requires-Dist: joblib ==1.3.2
Requires-Dist: json5 ==0.9.14
Requires-Dist: jsonpointer ==2.0
Requires-Dist: jsonschema ==4.19.0
Requires-Dist: jsonschema-specifications ==2023.7.1
Requires-Dist: jsonschema-with-format-nongpl ==4.19.0
Requires-Dist: jupyter ==1.0.0
Requires-Dist: jupyter-lsp ==2.2.0
Requires-Dist: jupyter-client ==8.3.0
Requires-Dist: jupyter-console ==6.6.3
Requires-Dist: jupyter-core ==5.3.0
Requires-Dist: jupyter-events ==0.7.0
Requires-Dist: jupyter-server ==2.7.1
Requires-Dist: jupyter-server-terminals ==0.4.4
Requires-Dist: jupyterlab ==4.0.5
Requires-Dist: jupyterlab-pygments ==0.2.2
Requires-Dist: jupyterlab-server ==2.24.0
Requires-Dist: jupyterlab-widgets ==3.0.8
Requires-Dist: kiwisolver ==1.4.4
Requires-Dist: krb5 ==1.17.2
Requires-Dist: lcms2 ==2.14
Requires-Dist: ld-impl-linux-64 ==2.40
Requires-Dist: lerc ==4.0.0
Requires-Dist: libblas ==3.9.0
Requires-Dist: libbrotlicommon ==1.0.9
Requires-Dist: libbrotlidec ==1.0.9
Requires-Dist: libbrotlienc ==1.0.9
Requires-Dist: libcblas ==3.9.0
Requires-Dist: libclang ==10.0.1
Requires-Dist: libdeflate ==1.14
Requires-Dist: libedit ==3.1.20191231
Requires-Dist: libevent ==2.1.10
Requires-Dist: libexpat ==2.5.0
Requires-Dist: libffi ==3.2.1
Requires-Dist: libgcc-ng ==13.1.0
Requires-Dist: libgfortran-ng ==13.1.0
Requires-Dist: libgfortran5 ==13.1.0
Requires-Dist: libglib ==2.66.3
Requires-Dist: libiconv ==1.17
Requires-Dist: liblapack ==3.9.0
Requires-Dist: libllvm10 ==10.0.1
Requires-Dist: libopenblas ==0.3.23
Requires-Dist: libpng ==1.6.39
Requires-Dist: libpq ==12.3
Requires-Dist: libprotobuf ==3.21.12
Requires-Dist: libsodium ==1.0.18
Requires-Dist: libsqlite ==3.42.0
Requires-Dist: libstdcxx-ng ==13.1.0
Requires-Dist: libtiff ==4.4.0
Requires-Dist: libtool ==2.4.7
Requires-Dist: libuuid ==2.38.1
Requires-Dist: libuv ==1.44.2
Requires-Dist: libwebp ==1.2.4
Requires-Dist: libwebp-base ==1.2.4
Requires-Dist: libxcb ==1.13
Requires-Dist: libxkbcommon ==0.10.0
Requires-Dist: libxml2 ==2.9.10
Requires-Dist: libzlib ==1.2.13
Requires-Dist: llvm-openmp ==16.0.6
Requires-Dist: markupsafe ==2.1.3
Requires-Dist: matplotlib ==3.7.1
Requires-Dist: matplotlib-base ==3.7.1
Requires-Dist: matplotlib-inline ==0.1.6
Requires-Dist: met-history-prediction ==1.0
Requires-Dist: mistune ==3.0.1
Requires-Dist: mkl ==2022.2.1
Requires-Dist: mpmath ==1.3.0
Requires-Dist: multiprocessing-logging ==0.3.4
Requires-Dist: munkres ==1.1.4
Requires-Dist: mysql-common ==8.0.32
Requires-Dist: mysql-libs ==8.0.32
Requires-Dist: nbclient ==0.8.0
Requires-Dist: nbconvert ==7.7.4
Requires-Dist: nbconvert-core ==7.7.4
Requires-Dist: nbconvert-pandoc ==7.7.4
Requires-Dist: nbformat ==5.9.2
Requires-Dist: ncurses ==6.4
Requires-Dist: nest-asyncio ==1.5.6
Requires-Dist: networkx ==3.1
Requires-Dist: notebook ==7.0.2
Requires-Dist: notebook-shim ==0.2.3
Requires-Dist: nspr ==4.35
Requires-Dist: nss ==3.92
Requires-Dist: numpy ==1.24.4
Requires-Dist: openjpeg ==2.5.0
Requires-Dist: openssl ==1.1.1
Requires-Dist: optree ==0.9.1
Requires-Dist: overrides ==7.4.0
Requires-Dist: packaging ==23.1
Requires-Dist: pandas ==2.0.3
Requires-Dist: pandoc ==3.1.3
Requires-Dist: pandocfilters ==1.5.0
Requires-Dist: pango ==1.42.4
Requires-Dist: parso ==0.8.3
Requires-Dist: patsy ==0.5.3
Requires-Dist: pcre ==8.45
Requires-Dist: pexpect ==4.8.0
Requires-Dist: pickleshare ==0.7.5
Requires-Dist: pillow ==9.2.0
Requires-Dist: pip ==23.2.1
Requires-Dist: pixman ==0.40.0
Requires-Dist: pkgutil-resolve-name ==1.3.10
Requires-Dist: platformdirs ==3.10.0
Requires-Dist: pooch ==1.7.0
Requires-Dist: prometheus-client ==0.17.1
Requires-Dist: prompt-toolkit ==3.0.39
Requires-Dist: psutil ==5.9.5
Requires-Dist: pthread-stubs ==0.4
Requires-Dist: ptyprocess ==0.7.0
Requires-Dist: pure-eval ==0.2.2
Requires-Dist: pycparser ==2.21
Requires-Dist: pydot ==1.4.2
Requires-Dist: pygments ==2.16.1
Requires-Dist: pygraphviz ==1.9
Requires-Dist: pyparsing ==3.0.9
Requires-Dist: pyqt ==5.12.3
Requires-Dist: pyqt-impl ==5.12.3
Requires-Dist: pyqt5-sip ==4.19.18
Requires-Dist: pyqtchart ==5.12
Requires-Dist: pyqtwebengine ==5.12.1
Requires-Dist: pyreadr ==0.4.9
Requires-Dist: pysocks ==1.7.1
Requires-Dist: python ==3.8.0
Requires-Dist: python-dateutil ==2.8.2
Requires-Dist: python-fastjsonschema ==2.18.0
Requires-Dist: python-graphviz ==0.20.1
Requires-Dist: python-json-logger ==2.0.7
Requires-Dist: python-tzdata ==2023.3
Requires-Dist: python-abi ==3.8
Requires-Dist: pytorch ==2.0.0
Requires-Dist: pytz ==2023.3
Requires-Dist: pyyaml ==6.0
Requires-Dist: pyzmq ==25.1.1
Requires-Dist: qt ==5.12.9
Requires-Dist: qtconsole ==5.4.3
Requires-Dist: qtconsole-base ==5.4.3
Requires-Dist: qtpy ==2.3.1
Requires-Dist: readline ==8.2
Requires-Dist: referencing ==0.30.2
Requires-Dist: requests ==2.31.0
Requires-Dist: rfc3339-validator ==0.1.4
Requires-Dist: rfc3986-validator ==0.1.1
Requires-Dist: rpds-py ==0.9.2
Requires-Dist: scipy ==1.10.1
Requires-Dist: seaborn ==0.12.2
Requires-Dist: seaborn-base ==0.12.2
Requires-Dist: send2trash ==1.8.2
Requires-Dist: setuptools ==68.1.2
Requires-Dist: six ==1.16.0
Requires-Dist: sleef ==3.5.1
Requires-Dist: sniffio ==1.3.0
Requires-Dist: soupsieve ==2.3.2.post1
Requires-Dist: sqlite ==3.42.0
Requires-Dist: stack-data ==0.6.2
Requires-Dist: statannot ==0.2.3
Requires-Dist: statsmodels ==0.14.0
Requires-Dist: sympy ==1.12
Requires-Dist: tbb ==2021.7.0
Requires-Dist: terminado ==0.17.1
Requires-Dist: tinycss2 ==1.2.1
Requires-Dist: tk ==8.6.12
Requires-Dist: tomli ==2.0.1
Requires-Dist: torchopt ==0.7.2
Requires-Dist: tornado ==6.3.3
Requires-Dist: tqdm ==4.66.1
Requires-Dist: traitlets ==5.9.0
Requires-Dist: typing-extensions ==4.7.1
Requires-Dist: typing-utils ==0.1.0
Requires-Dist: unicodedata2 ==15.0.0
Requires-Dist: uri-template ==1.3.0
Requires-Dist: urllib3 ==2.0.4
Requires-Dist: wcwidth ==0.2.6
Requires-Dist: webcolors ==1.13
Requires-Dist: webencodings ==0.5.1
Requires-Dist: websocket-client ==1.6.1
Requires-Dist: wheel ==0.41.2
Requires-Dist: widgetsnbextension ==4.0.8
Requires-Dist: xorg-kbproto ==1.0.7
Requires-Dist: xorg-libice ==1.0.10
Requires-Dist: xorg-libsm ==1.2.3
Requires-Dist: xorg-libx11 ==1.8.4
Requires-Dist: xorg-libxau ==1.0.11
Requires-Dist: xorg-libxdmcp ==1.1.3
Requires-Dist: xorg-libxext ==1.3.4
Requires-Dist: xorg-libxpm ==3.5.16
Requires-Dist: xorg-libxrender ==0.9.10
Requires-Dist: xorg-libxt ==1.3.0
Requires-Dist: xorg-renderproto ==0.11.1
Requires-Dist: xorg-xextproto ==7.3.0
Requires-Dist: xorg-xproto ==7.0.31
Requires-Dist: xz ==5.2.6
Requires-Dist: yaml ==0.2.5
Requires-Dist: zeromq ==4.3.4
Requires-Dist: zipp ==3.16.2
Requires-Dist: zlib ==1.2.13
Requires-Dist: zstd ==1.5.2
